{"_invocation_id": "347a6e3e-8922-431d-bbc8-87121381ffe4", "linked": {"0": {"name": "source.stock_analysis.stock.400_years_of_generated_dates_and_holidays", "type": "source", "succ": [46]}, "1": {"name": "source.stock_analysis.stock.symbols_valid_meta", "type": "source", "succ": [47]}, "2": {"name": "source.stock_analysis.stock.all_nasdaq_stock_info", "type": "source", "succ": [45]}, "3": {"name": "source.stock_analysis.stock.all_nasdaq_stock_history", "type": "source", "succ": [43]}, "4": {"name": "source.stock_analysis.stock.all_others_stock_info", "type": "source", "succ": [42]}, "5": {"name": "source.stock_analysis.stock.all_others_stock_history", "type": "source", "succ": [44]}, "6": {"name": "source.stock_analysis.stock.spy_2014_2024", "type": "source"}, "7": {"name": "source.stock_analysis.stock.spy_1993_2024", "type": "source"}, "8": {"name": "source.stock_analysis.stock.spus_2019_2024", "type": "source"}, "9": {"name": "source.stock_analysis.stock.hlal", "type": "source"}, "10": {"name": "source.stock_analysis.stock.aapl", "type": "source"}, "11": {"name": "source.stock_analysis.stock.abbv", "type": "source"}, "12": {"name": "source.stock_analysis.stock.adbe", "type": "source"}, "13": {"name": "source.stock_analysis.stock.amd", "type": "source"}, "14": {"name": "source.stock_analysis.stock.amzn", "type": "source"}, "15": {"name": "source.stock_analysis.stock.avgo", "type": "source"}, "16": {"name": "source.stock_analysis.stock.bac", "type": "source"}, "17": {"name": "source.stock_analysis.stock.brk-b", "type": "source"}, "18": {"name": "source.stock_analysis.stock.cost", "type": "source"}, "19": {"name": "source.stock_analysis.stock.crm", "type": "source"}, "20": {"name": "source.stock_analysis.stock.cvx", "type": "source"}, "21": {"name": "source.stock_analysis.stock.goog", "type": "source"}, "22": {"name": "source.stock_analysis.stock.googl", "type": "source"}, "23": {"name": "source.stock_analysis.stock.hd", "type": "source"}, "24": {"name": "source.stock_analysis.stock.jnj", "type": "source"}, "25": {"name": "source.stock_analysis.stock.jpm", "type": "source"}, "26": {"name": "source.stock_analysis.stock.ko", "type": "source"}, "27": {"name": "source.stock_analysis.stock.lly", "type": "source"}, "28": {"name": "source.stock_analysis.stock.ma", "type": "source"}, "29": {"name": "source.stock_analysis.stock.meta", "type": "source"}, "30": {"name": "source.stock_analysis.stock.mrk", "type": "source"}, "31": {"name": "source.stock_analysis.stock.msft", "type": "source"}, "32": {"name": "source.stock_analysis.stock.nflx", "type": "source"}, "33": {"name": "source.stock_analysis.stock.nvda", "type": "source"}, "34": {"name": "source.stock_analysis.stock.pep", "type": "source"}, "35": {"name": "source.stock_analysis.stock.pg", "type": "source"}, "36": {"name": "source.stock_analysis.stock.tmo", "type": "source"}, "37": {"name": "source.stock_analysis.stock.tsla", "type": "source"}, "38": {"name": "source.stock_analysis.stock.unh", "type": "source"}, "39": {"name": "source.stock_analysis.stock.v", "type": "source"}, "40": {"name": "source.stock_analysis.stock.wmt", "type": "source"}, "41": {"name": "source.stock_analysis.stock.xom", "type": "source"}, "42": {"name": "model.stock_analysis.base_all_others_stock_info", "type": "model", "succ": [54]}, "43": {"name": "model.stock_analysis.base_all_nasdaq_stock_history", "type": "model", "succ": [56]}, "44": {"name": "model.stock_analysis.base_all_others_stock_history", "type": "model", "succ": [56]}, "45": {"name": "model.stock_analysis.base_all_nasdaq_stock_info", "type": "model", "succ": [58]}, "46": {"name": "model.stock_analysis.base_calendar", "type": "model", "succ": [55]}, "47": {"name": "model.stock_analysis.base_symbols_meta", "type": "model", "succ": [57]}, "48": {"name": "model.stock_analysis.int_all_stock_history", "type": "model", "succ": [60]}, "49": {"name": "model.stock_analysis.stg_all_stock_history_weekly_monthly_yearly_price", "type": "model", "succ": [48]}, "50": {"name": "model.stock_analysis.stg_all_stock_weekly_price_movement", "type": "model", "succ": [48]}, "51": {"name": "model.stock_analysis.stg_all_stock_monthly_price_movement", "type": "model", "succ": [48]}, "52": {"name": "model.stock_analysis.stg_all_stock_yearly_price_movement", "type": "model", "succ": [48]}, "53": {"name": "model.stock_analysis.stg_all_stock_history_base", "type": "model", "succ": [49, 51, 50, 52]}, "54": {"name": "model.stock_analysis.stg_all_others_stock_info", "type": "model", "succ": [59]}, "55": {"name": "model.stock_analysis.stg_calendar", "type": "model", "succ": [53]}, "56": {"name": "model.stock_analysis.stg_all_stock_history", "type": "model", "succ": [53]}, "57": {"name": "model.stock_analysis.stg_symbols_meta", "type": "model", "succ": [60]}, "58": {"name": "model.stock_analysis.stg_all_nasdaq_stock_info", "type": "model", "succ": [59]}, "59": {"name": "model.stock_analysis.stg_all_stock_info", "type": "model", "succ": [60]}, "60": {"name": "model.stock_analysis.stock_analysis", "type": "model"}}}